icmd/__init__.py
icmd/version.py
icmd/core/__init__.py
icmd/core/client.py
icmd/core/credentials.py
icmd/core/slim_packages.py
icmd_python-1.5.8.dist-info/METADATA
icmd_python-1.5.8.dist-info/WHEEL
icmd_python-1.5.8.dist-info/top_level.txt
icmd_python-1.5.8.dist-info/RECORD
