Metadata-Version: 2.4
Name: icmd-python
Version: 1.5.8
Summary: Python client app for ICMD®
Author: QuesTek Innovations LLC
Requires-Python: >=3.12
Requires-Dist: cryptography
Requires-Dist: jupyter
Requires-Dist: numpy
Requires-Dist: pandas
Requires-Dist: pydantic
Requires-Dist: requests
Requires-Dist: scipy
Requires-Dist: xarray
Provides-Extra: dev
Requires-Dist: myst-nb; extra == "dev"
Requires-Dist: pytest; extra == "dev"
Requires-Dist: pytest-xdist; extra == "dev"
Requires-Dist: ruff; extra == "dev"
Requires-Dist: sphinx; extra == "dev"
Requires-Dist: sphinx-rtd-theme; extra == "dev"
Requires-Dist: pre-commit; extra == "dev"
